grid_tariff_calculator/__init__.py
grid_tariff_calculator/analysis.py
grid_tariff_calculator/app.py
grid_tariff_calculator/config.py
grid_tariff_calculator/grid_tariff_dataclasses.py
grid_tariff_calculator/tariff_calculator.py
grid_tariff_calculator-0.1.2.dist-info/LICENSE
grid_tariff_calculator-0.1.2.dist-info/METADATA
grid_tariff_calculator-0.1.2.dist-info/WHEEL
grid_tariff_calculator-0.1.2.dist-info/RECORD
